web_utils/__init__.py
web_utils/formatting.py
web_utils/middleware.py
web_utils/mixins.py
web_utils/models.py
web_utils/urls.py
web_utils/web.py
web_utils/templates/web_utils/analytics_gtag_snippet.html
web_utils/templates/web_utils/analytics_snippet.html
web_utils/templates/web_utils/paginator.html
web_utils/templatetags/__init__.py
web_utils/templatetags/analytics_tags.py
web_utils/templatetags/formatting_tags.py
web_utils/templatetags/html_tags.py
web_utils/templatetags/paginator_tags.py
web_utils/templatetags/settings_tags.py
web_utils/tests/__init__.py
web_utils/tests/test_middleware.py
web_utils/tests/test_templatetags.py
web_utils/tests/test_urls.py
web_utils/tests/test_web.py
web_utils/tests/url_conf.py
django_web_utils-0.4.6.dist-info/METADATA
django_web_utils-0.4.6.dist-info/WHEEL
django_web_utils-0.4.6.dist-info/top_level.txt
django_web_utils-0.4.6.dist-info/RECORD
